sysflow/__init__.py
sysflow/anima/__init__.py
sysflow/anima/png2gif.py
sysflow/anima/vid2gif.py
sysflow/bash/__init__.py
sysflow/bash/capitalize.py
sysflow/bash/merge_pdf.py
sysflow/bash/pkl_reader.py
sysflow/job/__init__.py
sysflow/job/slurm.py
sysflow/job/slurm_jobs.py
sysflow/job/utils.py
sysflow/log/__init__.py
sysflow/log/file_manager.py
sysflow/log/logger.py
sysflow/log/logger_utils.py
sysflow/parallel/__init__.py
sysflow/parallel/parallel.py
sysflow/utils/__init__.py
sysflow/utils/cache.py
sysflow/utils/colortext.py
sysflow/utils/common.py
sysflow/utils/file_manager.py
sysflow/utils/load_ckpt.py
sysflow/utils/logger.py
sysflow/utils/logging.py
sysflow/utils/recording.py
sysflow/utils/tb_logger.py
sysflow/utils/timer.py
sysflow/utils/word_index.py
sysflow/utils/common_utils/__init__.py
sysflow/utils/common_utils/bash_utils.py
sysflow/utils/common_utils/basic_utils.py
sysflow/utils/common_utils/choice_utils.py
sysflow/utils/common_utils/code_utils.py
sysflow/utils/common_utils/date_utils.py
sysflow/utils/common_utils/file_utils.py
sysflow/utils/common_utils/gpu_utils.py
sysflow/utils/common_utils/interactive.py
sysflow/utils/common_utils/io_utils.py
sysflow/utils/common_utils/knowledge_utils.py
sysflow/utils/common_utils/math_utils.py
sysflow/utils/common_utils/np_utils.py
sysflow/utils/common_utils/plotly_utils.py
sysflow/utils/common_utils/plt_utils.py
sysflow/utils/common_utils/re_utils.py
sysflow/utils/common_utils/sys_utils.py
sysflow/utils/common_utils/tensor_utils.py
sysflow/web/__init__.py
sysflow/web/arxiv/__init__.py
sysflow/web/arxiv/arxabs.py
sysflow/web/arxiv/arxate.py
sysflow/web/arxiv/arxb.py
sysflow/web/arxiv/arxcheck.py
sysflow/web/arxiv/arxdl.py
sysflow/web/arxiv/arxmd.py
sysflow/web/arxiv/arxrp.py
sysflow/web/arxiv/arxskim.py
sysflow/web/arxiv/ref2md.py
sysflow/web/email/__init__.py
sysflow/web/email/email_utils.py
sysflow/web/github/__init__.py
sysflow/web/github/github.py
sysflow/web/scirate/__init__.py
sysflow/web/scirate/scirate_check.py
sysflow-0.1.18.dist-info/LICENSE.txt
sysflow-0.1.18.dist-info/METADATA
sysflow-0.1.18.dist-info/WHEEL
sysflow-0.1.18.dist-info/entry_points.txt
sysflow-0.1.18.dist-info/top_level.txt
sysflow-0.1.18.dist-info/RECORD
