Metadata-Version: 2.2
Name: sysflow
Version: 0.1.18
Summary: A utility to saving time (time is flow)
Home-page: https://github.com/pypa/sampleproject
Author: Jimmy
Author-email: jiahaoyao.math@gmail.com
Project-URL: Bug Reports, https://github.com/pypa/sampleproject/issues
Project-URL: Funding, https://donate.pypi.org
Project-URL: Say Thanks!, http://saythanks.io/to/example
Project-URL: Source, https://github.com/pypa/sampleproject/
Keywords: utility toolbox for convenience
Classifier: Development Status :: 3 - Alpha
Classifier: Intended Audience :: Developers
Classifier: Intended Audience :: Education
Classifier: Intended Audience :: Science/Research
Classifier: Topic :: Scientific/Engineering :: Mathematics
Classifier: Topic :: Software Development :: Libraries :: Python Modules
Classifier: Topic :: Software Development :: Libraries
Classifier: License :: OSI Approved :: MIT License
Classifier: Programming Language :: Python :: 2
Classifier: Programming Language :: Python :: 2.7
Classifier: Programming Language :: Python :: 3
Classifier: Programming Language :: Python :: 3.5
Classifier: Programming Language :: Python :: 3.6
Classifier: Programming Language :: Python :: 3.7
Classifier: Programming Language :: Python :: 3.8
Requires-Python: >=2.7, !=3.0.*, !=3.1.*, !=3.2.*, !=3.3.*, !=3.4.*, <4
License-File: LICENSE.txt
Requires-Dist: bs4
Requires-Dist: schedule
Requires-Dist: python-dateutil
Requires-Dist: arxiv2bib
Requires-Dist: pybtex
Requires-Dist: bibtexparser
Requires-Dist: ruamel.yaml
Requires-Dist: pyperclip
Requires-Dist: rich
Requires-Dist: twint
Requires-Dist: ray
Requires-Dist: dask
Requires-Dist: joblib
Requires-Dist: loguru
Provides-Extra: dev
Requires-Dist: check-manifest; extra == "dev"
Provides-Extra: test
Requires-Dist: coverage; extra == "test"
Dynamic: author
Dynamic: author-email
Dynamic: classifier
Dynamic: description
Dynamic: description-content-type
Dynamic: home-page
Dynamic: keywords
Dynamic: project-url
Dynamic: provides-extra
Dynamic: requires-dist
Dynamic: requires-python
Dynamic: summary
